{"stats":{"minecraft:used":{"minecraft:dark_oak_stairs":23,"minecraft:enchanting_table":3,"minecraft:nether_brick_wall":3,"minecraft:jack_o_lantern":2,"minecraft:diorite":1,"minecraft:end_rod":132,"minecraft:iron_bars":33,"minecraft:iron_ore":6,"minecraft:sandstone_stairs":251,"minecraft:dropper":4,"minecraft:snow_block":1,"minecraft:smooth_quartz_slab":153,"minecraft:red_sandstone_slab":43,"minecraft:mycelium":11,"minecraft:spruce_planks":94,"minecraft:stone":5,"minecraft:cauldron":10,"minecraft:spruce_sign":91,"minecraft:quartz_stairs":255,"minecraft:clay":3,"minecraft:torch":3,"minecraft:white_wool":2,"minecraft:dark_oak_trapdoor":20,"minecraft:dirt":3,"minecraft:birch_pressure_plate":1,"minecraft:white_carpet":232,"minecraft:red_mushroom":6,"minecraft:jungle_planks":54,"minecraft:light_gray_terracotta":946,"minecraft:jungle_slab":32,"minecraft:acacia_leaves":3,"minecraft:note_block":31,"minecraft:jungle_trapdoor":12,"minecraft:infested_stone_bricks":3,"minecraft:smooth_red_sandstone_stairs":42,"minecraft:end_stone":248,"minecraft:obsidian":8,"minecraft:andesite_wall":3,"minecraft:redstone_torch":1,"minecraft:sticky_piston":1,"minecraft:mossy_cobblestone_stairs":86,"minecraft:black_terracotta":13,"minecraft:piston":4,"minecraft:lever":6,"minecraft:flower_pot":4,"minecraft:sea_lantern":136,"minecraft:black_wool":377,"minecraft:chipped_anvil":2,"minecraft:firework_rocket":2,"minecraft:daylight_detector":45,"minecraft:quartz_pillar":323,"minecraft:gray_shulker_box":20,"minecraft:quartz_slab":92,"minecraft:iron_block":25,"minecraft:lantern":7,"minecraft:grass_block":22,"minecraft:stone_button":44,"minecraft:lectern":12,"minecraft:polished_granite":14,"minecraft:smooth_quartz":13,"minecraft:iron_door":54,"minecraft:item_frame":9,"minecraft:acacia_fence_gate":8,"minecraft:green_carpet":1,"minecraft:birch_button":5,"minecraft:glowstone":189,"minecraft:repeater":28,"minecraft:potion":3,"minecraft:brown_carpet":254,"minecraft:iron_trapdoor":9,"minecraft:blue_shulker_box":15,"minecraft:gray_bed":2,"minecraft:sandstone_slab":55,"minecraft:andesite_stairs":5,"minecraft:lapis_block":1,"minecraft:smooth_stone_slab":34,"minecraft:observer":1},"minecraft:dropped":{"minecraft:activator_rail":1,"minecraft:elytra":1,"minecraft:item_frame":63,"minecraft:gold_nugget":1,"minecraft:brown_carpet":1,"minecraft:polished_granite":1},"minecraft:custom":{"minecraft:interact_with_anvil":1,"minecraft:tune_noteblock":9,"minecraft:play_one_minute":416775,"minecraft:open_shulker_box":6,"minecraft:pot_flower":3,"minecraft:leave_game":6,"minecraft:time_since_death":416775,"minecraft:time_since_rest":416775,"minecraft:sprint_one_cm":63299,"minecraft:walk_one_cm":858325,"minecraft:drop":6,"minecraft:fly_one_cm":1943327,"minecraft:crouch_one_cm":10601,"minecraft:sneak_time":7043,"minecraft:aviate_one_cm":90443,"minecraft:jump":959},"minecraft:picked_up":{"minecraft:iron_door":1,"minecraft:birch_button":2,"minecraft:elytra":1,"minecraft:polished_granite":1,"minecraft:item_frame":63,"minecraft:white_carpet":1,"minecraft:activator_rail":1,"minecraft:gold_nugget":1,"minecraft:porkchop":1,"minecraft:stone_button":5,"minecraft:brown_carpet":1,"minecraft:spruce_sign":2}},"DataVersion":2230}